api_codes/__init__.py
api_codes/goes_api.py
api_codes/login.py
api_codes/nexrad_api.py
api_codes/s3_api.py
backend/__init__.py
backend/access_token.py
backend/goes_file_retrieval_main.py
backend/main_goes18.py
backend/nexrad_file_retrieval_main.py
backend/nexrad_main.py
backend/nexrad_main_sqlite.py
backend/oauth2.py
backend/schema.py
backend/test.py
data/__init__.py
pages/01_login.py
pages/GOES.py
pages/Goes_file_link.py
pages/Nexrad.py
pages/Nexrad_file_link.py
pages/Nexrad_plot.py
pages/User_Signup.py
pages/__init__.py
pages/user_dashboard.py
team7_typer/__init__.py
team7_typer/typer_main.py
typernexrad-0.1.1.dist-info/METADATA
typernexrad-0.1.1.dist-info/WHEEL
typernexrad-0.1.1.dist-info/entry_points.txt
typernexrad-0.1.1.dist-info/top_level.txt
typernexrad-0.1.1.dist-info/RECORD
